telegram_notifier/__init__.py
telegram_notifier/telegram_notifier.py
telegram_notifier-0.2.dist-info/METADATA
telegram_notifier-0.2.dist-info/WHEEL
telegram_notifier-0.2.dist-info/top_level.txt
telegram_notifier-0.2.dist-info/RECORD
